zookeeper/__init__.py
zookeeper/test_version.py
zookeeper/core/__init__.py
zookeeper/core/cli.py
zookeeper/core/cli_test.py
zookeeper/core/component.py
zookeeper/core/component_test.py
zookeeper/core/factory.py
zookeeper/core/factory_registry.py
zookeeper/core/factory_test.py
zookeeper/core/field.py
zookeeper/core/field_test.py
zookeeper/core/partial_component.py
zookeeper/core/partial_component_test.py
zookeeper/core/task.py
zookeeper/core/task_test.py
zookeeper/core/utils.py
zookeeper/core/utils_test.py
zookeeper/tf/__init__.py
zookeeper/tf/dataset.py
zookeeper/tf/experiment.py
zookeeper/tf/preprocessing.py
zookeeper-1.3.4.dist-info/LICENSE
zookeeper-1.3.4.dist-info/METADATA
zookeeper-1.3.4.dist-info/WHEEL
zookeeper-1.3.4.dist-info/top_level.txt
zookeeper-1.3.4.dist-info/RECORD
