Metadata-Version: 2.1
Name: zookeeper
Version: 1.3.4
Summary: A small library for managing deep learning models, hyper-parameters and datasets
Home-page: https://github.com/larq/zookeeper
Author: Plumerai
Author-email: opensource@plumerai.com
License: Apache 2.0
Classifier: Development Status :: 3 - Alpha
Classifier: Intended Audience :: Developers
Classifier: Intended Audience :: Education
Classifier: Intended Audience :: Science/Research
Classifier: License :: OSI Approved :: Apache Software License
Classifier: Programming Language :: Python :: 3
Classifier: Programming Language :: Python :: 3 :: Only
Classifier: Programming Language :: Python :: 3.8
Classifier: Programming Language :: Python :: 3.9
Classifier: Programming Language :: Python :: 3.10
Classifier: Topic :: Scientific/Engineering
Classifier: Topic :: Scientific/Engineering :: Mathematics
Classifier: Topic :: Scientific/Engineering :: Artificial Intelligence
Classifier: Topic :: Software Development
Requires-Python: >=3.8
Provides-Extra: tensorflow
Provides-Extra: tensorflow_gpu
Provides-Extra: test
License-File: LICENSE
